debloch/__init__.py
debloch/bloch.py
debloch/bloch_pp.py
debloch/util.py
debloch-0.6.dist-info/LICENSE
debloch-0.6.dist-info/METADATA
debloch-0.6.dist-info/WHEEL
debloch-0.6.dist-info/top_level.txt
debloch-0.6.dist-info/RECORD
