Metadata-Version: 2.1
Name: debloch
Version: 0.6
Summary: Blochwave simulator for Continuous Electron Diffraction
Home-page: https://pypi.org/project/debloch
Author: Tarik Ronan Drevon
Author-email: tarik.drevon@stfc.ac.uk
License: UNKNOWN
Project-URL: Documentation, https://debloch.readthedocs.io/en/latest/
Project-URL: Source, https://github.com/ccp4/debloch
Platform: UNKNOWN
Classifier: Programming Language :: Python :: 3
Classifier: License :: OSI Approved :: BSD License 
Classifier: Operating System :: POSIX :: Linux 
Requires-Python: >=3.8
Requires-Dist: EDutilities (==0.6)
Requires-Dist: colorama
Requires-Dist: crystals
Requires-Dist: matplotlib
Requires-Dist: numpy
Requires-Dist: pandas
Requires-Dist: scipy
